setup.py
routine_day_night/__init__.py
routine_day_night/skinsteps.py
skincare_routine.egg-info/PKG-INFO
skincare_routine.egg-info/SOURCES.txt
skincare_routine.egg-info/dependency_links.txt
skincare_routine.egg-info/top_level.txt